README.md
setup.py
rocketDJEZIRIOuss/__init__.py
rocketDJEZIRIOuss/rocket.py
rocketDJEZIRIOuss/setup.py
rocketDJEZIRIOuss.egg-info/PKG-INFO
rocketDJEZIRIOuss.egg-info/SOURCES.txt
rocketDJEZIRIOuss.egg-info/dependency_links.txt
rocketDJEZIRIOuss.egg-info/requires.txt
rocketDJEZIRIOuss.egg-info/top_level.txt