Metadata-Version: 2.1
Name: rocketDJEZIRIOuss
Version: 1.0.0
Summary: An awesome package that does something
Home-page: http://pypi.python.org/pypi/rocketDJEZIRIOuss/
Author: OusDjeziri
Author-email: o.djeziri@esi-sba.dz
License: LICENSE.txt
